LICENSE
MANIFEST.in
README.rst
setup.py
Wanderer.egg-info/PKG-INFO
Wanderer.egg-info/SOURCES.txt
Wanderer.egg-info/dependency_links.txt
Wanderer.egg-info/entry_points.txt
Wanderer.egg-info/top_level.txt
tests/__init__.py
tests/test_app.py
tests/test_env.py
tests/test_filepath.py
tests/test_formatters.py
wanderer/__init__.py
wanderer/__main__.py
wanderer/_compat.py
wanderer/app.py
wanderer/cli.py
wanderer/config.py
wanderer/env.py
wanderer/filepath.py
wanderer/formatters.py
wanderer/models.py
wanderer/utils.py
wanderer/.wanderer/wanderer.yml
wanderer/.wanderer/configurations/.gitkeep
wanderer/.wanderer/environ/maya/icons/.gitkeep
wanderer/.wanderer/environ/maya/plug-ins/linux/.gitkeep
wanderer/.wanderer/environ/maya/plug-ins/osx/.gitkeep
wanderer/.wanderer/environ/maya/plug-ins/win/.gitkeep
wanderer/.wanderer/environ/maya/presets/.gitkeep
wanderer/.wanderer/environ/maya/scripts/userSetup.py
wanderer/.wanderer/environ/maya/scripts/AETemplates/.gitkeep
wanderer/.wanderer/environ/maya/shelves/.gitkeep
wanderer/.wanderer/environ/nuke/init.py
wanderer/.wanderer/environ/nuke/gizmos/.gitkeep
wanderer/.wanderer/environ/nuke/plugins/linux/.gitkeep
wanderer/.wanderer/environ/nuke/plugins/osx/.gitkeep
wanderer/.wanderer/environ/nuke/plugins/win/.gitkeep
wanderer/.wanderer/environ/nuke/python/.gitkeep
wanderer/.wanderer/environ/python/data/.gitkeep
wanderer/.wanderer/environ/python/lib/linux/.gitkeep
wanderer/.wanderer/environ/python/lib/osx/.gitkeep
wanderer/.wanderer/environ/python/lib/site-packages/.gitkeep
wanderer/.wanderer/environ/python/lib/win/.gitkeep
wanderer/.wanderer/environ/python/scripts/.gitkeep
wanderer/.wanderer/templates/abclayout/maya/work/workspace.mel
wanderer/.wanderer/templates/animation/maya/work/workspace.mel
wanderer/.wanderer/templates/asset/exchange/alembic/.gitkeep
wanderer/.wanderer/templates/asset/exchange/fbx/.gitkeep
wanderer/.wanderer/templates/asset/exchange/obj/.gitkeep
wanderer/.wanderer/templates/asset/review/.gitkeep
wanderer/.wanderer/templates/asset/shaders/.gitkeep
wanderer/.wanderer/templates/asset/textures/ai/.gitkeep
wanderer/.wanderer/templates/asset/textures/psd/.gitkeep
